datasets/__init__.py
datasets/dataset_cli.py
datasets/datasets.py
datasetstools-1.0.3.dist-info/DESCRIPTION.rst
datasetstools-1.0.3.dist-info/METADATA
datasetstools-1.0.3.dist-info/RECORD
datasetstools-1.0.3.dist-info/WHEEL
datasetstools-1.0.3.dist-info/entry_points.txt
datasetstools-1.0.3.dist-info/metadata.json
datasetstools-1.0.3.dist-info/top_level.txt
