Metadata-Version: 2.0
Name: datasetstools
Version: 1.0.3
Summary: UNKNOWN
Home-page: UNKNOWN
Author: Vit Listik
Author-email: tivvit@seznam.cz
License: MIT
Keywords: dataset management
Platform: UNKNOWN
Classifier: Development Status :: 5 - Production/Stable
Classifier: Intended Audience :: Developers
Classifier: Topic :: Software Development :: Libraries
Classifier: License :: OSI Approved :: MIT License
Classifier: Programming Language :: Python :: 2
Classifier: Programming Language :: Python :: 2.7
Classifier: Programming Language :: Python :: 3
Classifier: Programming Language :: Python :: 3.2
Classifier: Programming Language :: Python :: 3.3
Classifier: Programming Language :: Python :: 3.4
Classifier: Programming Language :: Python :: 3.5
Classifier: Programming Language :: Python :: Implementation :: PyPy
Requires-Dist: pyYAML
Requires-Dist: requests
Requires-Dist: six
